{"lastUsed":1655988617374,"path":"E:\/Cursos\/Workspaces\/CursoJava","projectCount":7,"recentFiles":[{"path":"\/10-Comportamento-de-memoria-arrays-listas\/src\/application","parentWorkspace":"E:\/Cursos\/Workspaces\/Teste","name":"Program2.java","lastModified":1655988152150,"locationURI":"file:\/E:\/Cursos\/Workspaces\/Teste\/10-Comportamento-de-memoria-arrays-listas\/src\/application\/Program2.java"},{"path":"\/10-Comportamento-de-memoria-arrays-listas\/src\/application","parentWorkspace":"E:\/Cursos\/Workspaces\/Teste","name":"Program.java","lastModified":1655988154294,"locationURI":"file:\/E:\/Cursos\/Workspaces\/Teste\/10-Comportamento-de-memoria-arrays-listas\/src\/application\/Program.java"},{"path":"\/06-Estrutura-Repetitiva\/src\/main","parentWorkspace":"E:\/Cursos\/Workspaces\/Teste","name":"DoWhile.java","lastModified":1655987888613,"locationURI":"file:\/E:\/Cursos\/Workspaces\/Teste\/06-Estrutura-Repetitiva\/src\/main\/DoWhile.java"},{"path":"\/08-Introducao-a-programacao-orientada-objetos\/src\/entities","parentWorkspace":"E:\/Cursos\/Workspaces\/Teste","name":"Product.java","lastModified":1655987961937,"locationURI":"file:\/E:\/Cursos\/Workspaces\/Teste\/08-Introducao-a-programacao-orientada-objetos\/src\/entities\/Product.java"},{"path":"\/08-Introducao-a-programacao-orientada-objetos\/src\/entities","parentWorkspace":"E:\/Cursos\/Workspaces\/Teste","name":"Triangle.java","lastModified":1655987961031,"locationURI":"file:\/E:\/Cursos\/Workspaces\/Teste\/08-Introducao-a-programacao-orientada-objetos\/src\/entities\/Triangle.java"},{"path":"\/03-Introducao-a-linguagem-java\/src\/main","parentWorkspace":"E:\/Cursos\/Workspaces\/Teste","name":"ProcessamentoDeDados.java","lastModified":1655987452325,"locationURI":"file:\/E:\/Cursos\/Workspaces\/Teste\/03-Introducao-a-linguagem-java\/src\/main\/ProcessamentoDeDados.java"},{"path":"\/05-Estrutura-Comdicional\/src\/main","parentWorkspace":"E:\/Cursos\/Workspaces\/Teste","name":"EstruturaCondicional.java","lastModified":1655987836439,"locationURI":"file:\/E:\/Cursos\/Workspaces\/Teste\/05-Estrutura-Comdicional\/src\/main\/EstruturaCondicional.java"},{"path":"\/08-Introducao-a-programacao-orientada-objetos\/src\/program","parentWorkspace":"E:\/Cursos\/Workspaces\/Teste","name":"ProgramTriangle.java","lastModified":1655987988538,"locationURI":"file:\/E:\/Cursos\/Workspaces\/Teste\/08-Introducao-a-programacao-orientada-objetos\/src\/program\/ProgramTriangle.java"},{"path":"\/06-Estrutura-Repetitiva\/src\/main","parentWorkspace":"E:\/Cursos\/Workspaces\/Teste","name":"While.java","lastModified":1655987876461,"locationURI":"file:\/E:\/Cursos\/Workspaces\/Teste\/06-Estrutura-Repetitiva\/src\/main\/While.java"},{"path":"\/09-Construtores-palavra-this-sobrecarga-encapsulamento\/src\/application","parentWorkspace":"E:\/Cursos\/Workspaces\/Teste","name":"Program.java","lastModified":1655988102016,"locationURI":"file:\/E:\/Cursos\/Workspaces\/Teste\/09-Construtores-palavra-this-sobrecarga-encapsulamento\/src\/application\/Program.java"},{"path":"\/09-Construtores-palavra-this-sobrecarga-encapsulamento\/src\/entities","parentWorkspace":"E:\/Cursos\/Workspaces\/Teste","name":"Product.java","lastModified":1655988106865,"locationURI":"file:\/E:\/Cursos\/Workspaces\/Teste\/09-Construtores-palavra-this-sobrecarga-encapsulamento\/src\/entities\/Product.java"},{"path":"\/06-Estrutura-Repetitiva\/src\/main","parentWorkspace":"E:\/Cursos\/Workspaces\/Teste","name":"For.java","lastModified":1655987881802,"locationURI":"file:\/E:\/Cursos\/Workspaces\/Teste\/06-Estrutura-Repetitiva\/src\/main\/For.java"},{"path":"\/08-Introducao-a-programacao-orientada-objetos\/src\/program","parentWorkspace":"E:\/Cursos\/Workspaces\/Teste","name":"ProgramProduct.java","lastModified":1655987978292,"locationURI":"file:\/E:\/Cursos\/Workspaces\/Teste\/08-Introducao-a-programacao-orientada-objetos\/src\/program\/ProgramProduct.java"}]}